.gitignore
CHANGES.txt
LICENSE.txt
MANIFEST.in
README.txt
setup.py
pyramid_socketio/__init__.py
pyramid_socketio/io.py
pyramid_socketio/pasteserve.py
pyramid_socketio/serve.py
pyramid_socketio/servereload.py
pyramid_socketio.egg-info/PKG-INFO
pyramid_socketio.egg-info/SOURCES.txt
pyramid_socketio.egg-info/dependency_links.txt
pyramid_socketio.egg-info/entry_points.txt
pyramid_socketio.egg-info/not-zip-safe
pyramid_socketio.egg-info/requires.txt
pyramid_socketio.egg-info/top_level.txt
pyramid_socketio/gunicorn/__init__.py
pyramid_socketio/gunicorn/workers.py