Metadata-Version: 1.0
Name: pyramid-socketio
Version: 0.9
Summary: Gevent-based Socket.IO pyramid integration and helpers
Home-page: https://github.com/abourget/pyramid_socketio
Author: Alexandre Bourget
Author-email: alex@bourget.cc
License: UNKNOWN
Keywords: web wsgi pylons pyramid websocket python gevent socketio socket.io
Platform: UNKNOWN
Classifier: Programming Language :: Python
Classifier: Framework :: Pylons
Classifier: Framework :: BFG
Classifier: Topic :: Internet :: WWW/HTTP
